template_test_repo/__init__.py
template_test_repo-1.0.0.dist-info/LICENSE
template_test_repo-1.0.0.dist-info/METADATA
template_test_repo-1.0.0.dist-info/WHEEL
template_test_repo-1.0.0.dist-info/top_level.txt
template_test_repo-1.0.0.dist-info/RECORD
