Metadata-Version: 2.1
Name: template-test-repo
Version: 1.0.0
Summary: An example library
Home-page: https://web.hypothes.is/
Author: Hypothesis Engineering Team
Author-email: eng@list.hypothes.is
Maintainer: Hypothesis Engineering Team
Maintainer-email: eng@list.hypothes.is
License: License :: OSI Approved :: BSD License
Project-URL: Source, https://github.com/hypothesis/h-cookiecutter-pypackage
Platform: Operating System :: OS Independent
Classifier: Development Status :: 2 - Pre-Alpha
Classifier: Programming Language :: Python :: 3.6
Provides-Extra: tests
Requires-Dist: pytest ; extra == 'tests'
Requires-Dist: coverage ; extra == 'tests'
